LICENSE
MANIFEST.in
README.rst
setup.cfg
setup.py
versioneer.py
orographic_precipitation/__init__.py
orographic_precipitation/_version.py
orographic_precipitation/fastscape_ext.py
orographic_precipitation/orographic_precipitation.py
orographic_precipitation.egg-info/PKG-INFO
orographic_precipitation.egg-info/SOURCES.txt
orographic_precipitation.egg-info/dependency_links.txt
orographic_precipitation.egg-info/requires.txt
orographic_precipitation.egg-info/top_level.txt
orographic_precipitation/tests/WIPtest_orographic_drainage_discharge.py
orographic_precipitation/tests/__init__.py
orographic_precipitation/tests/fixture_orographic_precipitation.py
orographic_precipitation/tests/test_orographic_precipitation.py
orographic_precipitation/tests/test_process_orographic_precipitation.py