Metadata-Version: 2.1
Name: orographic-precipitation
Version: 1.0
Summary: Linear Theory of Orographic Precipitation
Home-page: https://github.com/rlange2/orographic-precipitation
Maintainer: Raphael Lange
Maintainer-email: raphael.lange@gfz-potsdam.de
License: MIT
Download-URL: https://github.com/rlange2/orographic-precipitation/archive/0.1a.tar.gz
Platform: UNKNOWN
Requires-Python: >=3.6
